animalsgonewild/__init__.py
animalsgonewild/animalsgonewild.py
animalsgonewild/images/duck.jpg
animalsgonewild/images/giraffe.jpg
animalsgonewild/images/monkey.jpg
animalsgonewild/images/monkey1.jpg
animalsgonewild/images/monkey2.jfif
animalsgonewild/images/monkey2.jpg
animalsgonewild/images/whale.jpg
animalsgonewild/imgs/bonus.jpeg
animalsgonewild/imgs/dumb_Duck.jpeg
animalsgonewild/imgs/dumb_Giraffe.jpeg
animalsgonewild/imgs/dumb_Monkey.jpeg
animalsgonewild/imgs/dumb_Whale.jpeg
animalsgonewild/imgs/smart_Duck.jpeg
animalsgonewild/imgs/smart_Giraffe.jpeg
animalsgonewild/imgs/smart_Monkey.jpeg
animalsgonewild/imgs/smart_Whale.jpeg
animalsgonewild-1.1.8.dist-info/LICENSE
animalsgonewild-1.1.8.dist-info/WHEEL
animalsgonewild-1.1.8.dist-info/METADATA
animalsgonewild-1.1.8.dist-info/RECORD
