Metadata-Version: 2.1
Name: animalsgonewild
Version: 1.1.8
Summary: Behaves like the text equivalent of an animal inspired Instagram filter
License: MIT
Author: DSCI 524 - Team 16
Requires-Python: >=3.9,<4.0
Classifier: License :: OSI Approved :: MIT License
Classifier: Programming Language :: Python :: 3
Classifier: Programming Language :: Python :: 3.10
Classifier: Programming Language :: Python :: 3.9
Requires-Dist: Pillow (>=9.0.0,<10.0.0)
Requires-Dist: codecov (>=2.1.12,<3.0.0)
Requires-Dist: newspaper3k (>=0.2.8,<0.3.0)
Requires-Dist: nltk (>=3.6.7,<4.0.0)
Requires-Dist: numpy (>=1.22.1,<2.0.0)
Requires-Dist: wordcloud (>=1.8.1,<2.0.0)
